MANIFEST.in
README.rst
TITLE.txt
lh-agpl3-LICENSE.txt
setup.py
./bin/classicCarsScraperParams.py
./bin/icmClassicCarsWebScraper.py
./bin/scrapeExample.py
./bin/scraperClassicCars.py
unisos/__init__.py
unisos.wsfClassicCars.egg-info/PKG-INFO
unisos.wsfClassicCars.egg-info/SOURCES.txt
unisos.wsfClassicCars.egg-info/dependency_links.txt
unisos.wsfClassicCars.egg-info/namespace_packages.txt
unisos.wsfClassicCars.egg-info/not-zip-safe
unisos.wsfClassicCars.egg-info/requires.txt
unisos.wsfClassicCars.egg-info/top_level.txt
unisos/wsfClassicCars/__init__.py