Metadata-Version: 2.1
Name: unisos.wsfClassicCars
Version: 0.1
Summary: unisos.wsfClassicCars: Classic Cars App Based On WSF (Web Scraping Framework)
Home-page: http://www.by-star.net/PLPC/180047
Download-URL: http://www.by-star.net/PLPC/180047
Author: Mohsen Banan
Author-email: libre@mohsen.1.banan.byname.net
Maintainer: Mohsen Banan
Maintainer-email: libre@mohsen.1.banan.byname.net
License: AGPL
Platform: UNKNOWN
Classifier: Development Status :: 3 - Alpha
Classifier: Intended Audience :: Developers
Classifier: License :: OSI Approved :: GNU Affero General Public License v3
Classifier: Operating System :: POSIX
Classifier: Programming Language :: Python
Classifier: Topic :: Software Development :: Libraries
Classifier: Topic :: Software Development :: Libraries :: Python Modules
